odoo/addons/website_menu_icon/README.rst
odoo/addons/website_menu_icon/__init__.py
odoo/addons/website_menu_icon/__manifest__.py
odoo/addons/website_menu_icon/i18n/website_menu_icon.pot
odoo/addons/website_menu_icon/models/__init__.py
odoo/addons/website_menu_icon/models/website_menu.py
odoo/addons/website_menu_icon/readme/CONFIGURE.rst
odoo/addons/website_menu_icon/readme/CONTRIBUTORS.rst
odoo/addons/website_menu_icon/readme/DESCRIPTION.rst
odoo/addons/website_menu_icon/static/description/edit_item.png
odoo/addons/website_menu_icon/static/description/edit_menu.png
odoo/addons/website_menu_icon/static/description/icon.png
odoo/addons/website_menu_icon/static/description/index.html
odoo/addons/website_menu_icon/static/description/menu_sample.png
odoo/addons/website_menu_icon/static/src/js/content.js
odoo/addons/website_menu_icon/static/src/xml/website.contentMenu.xml
odoo/addons/website_menu_icon/views/assets.xml
odoo/addons/website_menu_icon/views/website_menu_icon.xml
odoo13_addon_website_menu_icon-13.0.1.0.1.dist-info/METADATA
odoo13_addon_website_menu_icon-13.0.1.0.1.dist-info/WHEEL
odoo13_addon_website_menu_icon-13.0.1.0.1.dist-info/top_level.txt
odoo13_addon_website_menu_icon-13.0.1.0.1.dist-info/RECORD
