Metadata-Version: 2.1
Name: odoo13-addon-website-menu-icon
Version: 13.0.1.0.1
Summary: Provides possibility to define icons/images for menus. These can be then rendered in a custom theme. It also brings back option for opening new window.
Home-page: https://github.com/OCA/website
Author: Radovan Skolnik, Odoo Community Association (OCA)
Author-email: support@odoo-community.org
License: AGPL-3
Platform: UNKNOWN
Classifier: Programming Language :: Python
Classifier: Framework :: Odoo
Classifier: Framework :: Odoo :: 13.0
Classifier: License :: OSI Approved :: GNU Affero General Public License v3
Requires-Python: >=3.5
Requires-Dist: odoo (<13.1dev,>=13.0a)
